xayah/__init__.py
xayah/check.py
xayah/severity_level.py
xayah/shared_data.py
xayah/step.py
xayah/test_case.py
xayah/test_result.py
xayah/test_result_models.py
xayah/test_suite.py
xayah-0.0.8.dist-info/LICENSE
xayah-0.0.8.dist-info/METADATA
xayah-0.0.8.dist-info/WHEEL
xayah-0.0.8.dist-info/top_level.txt
xayah-0.0.8.dist-info/RECORD
