Metadata-Version: 2.1
Name: xayah
Version: 0.0.8
Summary: A lightweight testing tool with test report functionality
Home-page: https://github.com/ualisars/xayah
License: MIT
License-File: LICENSE
Requires-Dist: pydantic (==1.7.3)
